finetrainers/__init__.py
finetrainers/args.py
finetrainers/config.py
finetrainers/constants.py
finetrainers/logging.py
finetrainers/optimizer.py
finetrainers/state.py
finetrainers/trackers.py
finetrainers/typing.py
finetrainers/data/__init__.py
finetrainers/data/_artifact.py
finetrainers/data/dataloader.py
finetrainers/data/dataset.py
finetrainers/data/precomputation.py
finetrainers/data/sampler.py
finetrainers/functional/__init__.py
finetrainers/functional/diffusion.py
finetrainers/functional/image.py
finetrainers/functional/normalization.py
finetrainers/functional/text.py
finetrainers/functional/video.py
finetrainers/models/__init__.py
finetrainers/models/attention_dispatch.py
finetrainers/models/modeling_utils.py
finetrainers/models/utils.py
finetrainers/models/cogvideox/__init__.py
finetrainers/models/cogvideox/base_specification.py
finetrainers/models/cogvideox/utils.py
finetrainers/models/cogview4/__init__.py
finetrainers/models/cogview4/base_specification.py
finetrainers/models/cogview4/control_specification.py
finetrainers/models/flux/__init__.py
finetrainers/models/flux/base_specification.py
finetrainers/models/hunyuan_video/__init__.py
finetrainers/models/hunyuan_video/base_specification.py
finetrainers/models/ltx_video/__init__.py
finetrainers/models/ltx_video/base_specification.py
finetrainers/models/wan/__init__.py
finetrainers/models/wan/base_specification.py
finetrainers/models/wan/control_specification.py
finetrainers/parallel/__init__.py
finetrainers/parallel/accelerate.py
finetrainers/parallel/base.py
finetrainers/parallel/deepspeed.py
finetrainers/parallel/ptd.py
finetrainers/parallel/utils.py
finetrainers/patches/__init__.py
finetrainers/patches/utils.py
finetrainers/processors/__init__.py
finetrainers/processors/base.py
finetrainers/processors/canny.py
finetrainers/processors/clip.py
finetrainers/processors/glm.py
finetrainers/processors/llama.py
finetrainers/processors/t5.py
finetrainers/processors/text.py
finetrainers/trainer/__init__.py
finetrainers-0.2.0.dist-info/LICENSE
finetrainers-0.2.0.dist-info/METADATA
finetrainers-0.2.0.dist-info/WHEEL
finetrainers-0.2.0.dist-info/top_level.txt
finetrainers-0.2.0.dist-info/RECORD
