Metadata-Version: 2.1
Name: finetrainers
Version: 0.2.0
Summary: Finetrainers is a work-in-progress library to support (accessible) training of diffusion models
Home-page: https://github.com/a-r-r-o-w/finetrainers
Author: Aryan V S
Author-email: contact.aryanvs@gmail.com
License: Apache-2.0
Classifier: Development Status :: 1 - Planning
Classifier: Intended Audience :: Science/Research
Classifier: Intended Audience :: Developers
Classifier: Intended Audience :: Education
Classifier: Programming Language :: Python :: 3
Classifier: Programming Language :: Python :: 3.8
Classifier: Programming Language :: Python :: 3.9
Classifier: Programming Language :: Python :: 3.10
Classifier: Operating System :: Microsoft :: Windows
Classifier: Operating System :: Unix
Classifier: License :: OSI Approved :: MIT License
Classifier: Topic :: Scientific/Engineering :: Artificial Intelligence
Requires-Python: >=3.8.0
License-File: LICENSE
Requires-Dist: accelerate
Requires-Dist: bitsandbytes
Requires-Dist: datasets>=3.3.2
Requires-Dist: diffusers>=0.32.1
Requires-Dist: transformers>=4.45.2
Requires-Dist: huggingface_hub
Requires-Dist: hf_transfer>=0.1.8
Requires-Dist: peft>=0.13.0
Requires-Dist: decord>=0.6.0
Requires-Dist: wandb
Requires-Dist: pandas
Requires-Dist: torch>=2.5.1
Requires-Dist: torchvision>=0.20.1
Requires-Dist: torchdata>=0.10.1
Requires-Dist: torchao>=0.7.0
Requires-Dist: sentencepiece>=0.2.0
Requires-Dist: imageio-ffmpeg>=0.5.1
Requires-Dist: numpy>=1.26.4
Requires-Dist: kornia>=0.7.3
Requires-Dist: ruff==0.9.10
Provides-Extra: dev
Requires-Dist: pytest==8.3.2; extra == "dev"
Requires-Dist: ruff==0.1.5; extra == "dev"
